memesis/__init__.py
memesis/app.py
memesis/mnemosyne.jpg
memesis/run.py
memesis-0.3.4.dist-info/LICENSE
memesis-0.3.4.dist-info/METADATA
memesis-0.3.4.dist-info/WHEEL
memesis-0.3.4.dist-info/top_level.txt
memesis-0.3.4.dist-info/RECORD
