Metadata-Version: 2.1
Name: memesis
Version: 0.3.4
Summary: Custodian and live editor of your LLM's memory
Home-page: https://github.com/ptarau/mnemosyne.git
Author: Paul Tarau
Author-email: ptarau@gmail.com
License: MIT
License-File: LICENSE
Requires-Dist: openai
Requires-Dist: pandas
Requires-Dist: streamlit
Requires-Dist: deepllm
